pyfuppes/__init__.py
pyfuppes/avgbinmap.py
pyfuppes/dictstuff.py
pyfuppes/filters.py
pyfuppes/geo.py
pyfuppes/interpolate.py
pyfuppes/misc.py
pyfuppes/monotonicity.py
pyfuppes/na1001.py
pyfuppes/numberstring.py
pyfuppes/plottools.py
pyfuppes/py.typed
pyfuppes/timeconversion.py
pyfuppes/timecorr.py
pyfuppes/txt2dict.py
pyfuppes/na1001_backend/__init__.py
pyfuppes/na1001_backend/nasa_ames_1001_rw.py
pyfuppes/na1001_backend/nasa_ames_1001_tools.py
pyfuppes-0.7.1.dist-info/METADATA
pyfuppes-0.7.1.dist-info/WHEEL
pyfuppes-0.7.1.dist-info/licenses/LICENSE.md
pyfuppes-0.7.1.dist-info/RECORD
